Workbook

Sheet 全明細
A1: カード | B1: 明細月 | C1: 利用日 | D1: 利用月 | E1: 利用先 | F1: 勘定科目 | G1: 金額(円) | H1: 備考
A2: AMEX(Marriott Bonvoy) | B2: 2025-12 | C2: 45958 | D2: =TEXT(C2,"YYYY-MM") -> 2025-10 | E2: 東邦ガス(10月分) | F2: 水道光熱費 | G2: 2408
A3: AMEX(Marriott Bonvoy) | B3: 2025-12 | C3: 45961 | D3: =TEXT(C3,"YYYY-MM") -> 2025-10 | E3: GOアプリ(乗車料金) | F3: 旅費交通費 | G3: 2000
A4: AMEX(Marriott Bonvoy) | B4: 2025-12 | C4: 45961 | D4: =TEXT(C4,"YYYY-MM") -> 2025-10 | E4: GOアプリ(乗車料金) | F4: 旅費交通費 | G4: 2700
A5: AMEX(Marriott Bonvoy) | B5: 2025-12 | C5: 45961 | D5: =TEXT(C5,"YYYY-MM") -> 2025-10 | E5: ソフトバンクM | F5: 通信費 | G5: 4392
A6: AMEX(Marriott Bonvoy) | B6: 2025-12 | C6: 45961 | D6: =TEXT(C6,"YYYY-MM") -> 2025-10 | E6: ソフトバンクM | F6: 通信費 | G6: 1617
A7: AMEX(Marriott Bonvoy) | B7: 2025-12 | C7: 45961 | D7: =TEXT(C7,"YYYY-MM") -> 2025-10 | E7: ソフトバンクM | F7: 通信費 | G7: 1764
A8: AMEX(Marriott Bonvoy) | B8: 2025-12 | C8: 45961 | D8: =TEXT(C8,"YYYY-MM") -> 2025-10 | E8: ソフトバンクM | F8: 通信費 | G8: 1544
A9: AMEX(Marriott Bonvoy) | B9: 2025-12 | C9: 45961 | D9: =TEXT(C9,"YYYY-MM") -> 2025-10 | E9: ソフトバンクM | F9: 通信費 | G9: 2852
A10: AMEX(Marriott Bonvoy) | B10: 2025-12 | C10: 45962 | D10: =TEXT(C10,"YYYY-MM") -> 2025-11 | E10: ナビパーク(千葉市美浜区) | F10: 車両費 | G10: 200 | H10: 駐車場
A11: AMEX(Marriott Bonvoy) | B11: 2025-12 | C11: 45962 | D11: =TEXT(C11,"YYYY-MM") -> 2025-11 | E11: GMOとくとくBB | F11: 通信費 | G11: 5121 | H11: ネット回線
A12: AMEX(Marriott Bonvoy) | B12: 2025-12 | C12: 45962 | D12: =TEXT(C12,"YYYY-MM") -> 2025-11 | E12: 楽天ペイ バルめし山田 | F12: 飲食費 | G12: 13620
A13: AMEX(Marriott Bonvoy) | B13: 2025-12 | C13: 45962 | D13: =TEXT(C13,"YYYY-MM") -> 2025-11 | E13: ETC 東日本高速 | F13: 車両費 | G13: 270
A14: AMEX(Marriott Bonvoy) | B14: 2025-12 | C14: 45962 | D14: =TEXT(C14,"YYYY-MM") -> 2025-11 | E14: ETC 東日本高速 | F14: 車両費 | G14: 270
A15: AMEX(Marriott Bonvoy) | B15: 2025-12 | C15: 45962 | D15: =TEXT(C15,"YYYY-MM") -> 2025-11 | E15: ETC 首都高 | F15: 車両費 | G15: 840
A16: AMEX(Marriott Bonvoy) | B16: 2025-12 | C16: 45962 | D16: =TEXT(C16,"YYYY-MM") -> 2025-11 | E16: ETC 首都高 | F16: 車両費 | G16: 900
A17: AMEX(Marriott Bonvoy) | B17: 2025-12 | C17: 45963 | D17: =TEXT(C17,"YYYY-MM") -> 2025-11 | E17: 丸善 有明ガーデン店 | F17: 新聞図書費 | G17: 1760
A18: AMEX(Marriott Bonvoy) | B18: 2025-12 | C18: 45963 | D18: =TEXT(C18,"YYYY-MM") -> 2025-11 | E18: 住友不動産SC有明ガーデン | F18: 雑費・その他 | G18: 6070
A19: AMEX(Marriott Bonvoy) | B19: 2025-12 | C19: 45963 | D19: =TEXT(C19,"YYYY-MM") -> 2025-11 | E19: ENEOS | F19: 車両費 | G19: 7365 | H19: ガソリン
A20: AMEX(Marriott Bonvoy) | B20: 2025-12 | C20: 45963 | D20: =TEXT(C20,"YYYY-MM") -> 2025-11 | E20: ETC 首都高 | F20: 車両費 | G20: 660
A21: AMEX(Marriott Bonvoy) | B21: 2025-12 | C21: 45963 | D21: =TEXT(C21,"YYYY-MM") -> 2025-11 | E21: ETC 首都高 | F21: 車両費 | G21: 630
A22: AMEX(Marriott Bonvoy) | B22: 2025-12 | C22: 45964 | D22: =TEXT(C22,"YYYY-MM") -> 2025-11 | E22: 東京電力(10月分) | F22: 水道光熱費 | G22: 4168
A23: AMEX(Marriott Bonvoy) | B23: 2025-12 | C23: 45964 | D23: =TEXT(C23,"YYYY-MM") -> 2025-11 | E23: ナビパーク | F23: 車両費 | G23: 200 | H23: 駐車場
A24: AMEX(Marriott Bonvoy) | B24: 2025-12 | C24: 45964 | D24: =TEXT(C24,"YYYY-MM") -> 2025-11 | E24: タイムズ東尾久第19 | F24: 車両費 | G24: 1100 | H24: 駐車場
A25: AMEX(Marriott Bonvoy) | B25: 2025-12 | C25: 45965 | D25: =TEXT(C25,"YYYY-MM") -> 2025-11 | E25: Apple iTunes Store | F25: サブスク・ソフトウェア | G25: 1500
A26: AMEX(Marriott Bonvoy) | B26: 2025-12 | C26: 45965 | D26: =TEXT(C26,"YYYY-MM") -> 2025-11 | E26: アマゾン | F26: 消耗品費・備品 | G26: 31023
A27: AMEX(Marriott Bonvoy) | B27: 2025-12 | C27: 45965 | D27: =TEXT(C27,"YYYY-MM") -> 2025-11 | E27: 鷹丸鮮魚店4号店 | F27: 飲食費 | G27: 1380
A28: AMEX(Marriott Bonvoy) | B28: 2025-12 | C28: 45965 | D28: =TEXT(C28,"YYYY-MM") -> 2025-11 | E28: アップルストア新宿 | F28: 消耗品費・備品 | G28: 45600 | H28: Apple製品
A29: AMEX(Marriott Bonvoy) | B29: 2025-12 | C29: 45965 | D29: =TEXT(C29,"YYYY-MM") -> 2025-11 | E29: タリーズコーヒー新宿 | F29: 飲食費 | G29: 620 | H29: カフェ
A30: AMEX(Marriott Bonvoy) | B30: 2025-12 | C30: 45966 | D30: =TEXT(C30,"YYYY-MM") -> 2025-11 | E30: ヒモノ照ラス(名古屋) | F30: 飲食費 | G30: 4136
A31: AMEX(Marriott Bonvoy) | B31: 2025-12 | C31: 45966 | D31: =TEXT(C31,"YYYY-MM") -> 2025-11 | E31: GOOGLE ONE | F31: サブスク・ソフトウェア | G31: 2900
A32: AMEX(Marriott Bonvoy) | B32: 2025-12 | C32: 45966 | D32: =TEXT(C32,"YYYY-MM") -> 2025-11 | E32: 名古屋駅店舗 | F32: 雑費・その他 | G32: 9630
A33: AMEX(Marriott Bonvoy) | B33: 2025-12 | C33: 45966 | D33: =TEXT(C33,"YYYY-MM") -> 2025-11 | E33: エクスプレス予約 | F33: 旅費交通費 | G33: 21760 | H33: 新幹線
A34: AMEX(Marriott Bonvoy) | B34: 2025-12 | C34: 45966 | D34: =TEXT(C34,"YYYY-MM") -> 2025-11 | E34: エクスプレス予約 | F34: 旅費交通費 | G34: 21760 | H34: 新幹線
A35: AMEX(Marriott Bonvoy) | B35: 2025-12 | C35: 45966 | D35: =TEXT(C35,"YYYY-MM") -> 2025-11 | E35: ゲートタワー(名古屋) | F35: 雑費・その他 | G35: 1040
A36: AMEX(Marriott Bonvoy) | B36: 2025-12 | C36: 45967 | D36: =TEXT(C36,"YYYY-MM") -> 2025-11 | E36: 鷹丸鮮魚店4号店 | F36: 飲食費 | G36: 1380
A37: AMEX(Marriott Bonvoy) | B37: 2025-12 | C37: 45968 | D37: =TEXT(C37,"YYYY-MM") -> 2025-11 | E37: 鷹丸鮮魚店4号店 | F37: 飲食費 | G37: 1580
A38: AMEX(Marriott Bonvoy) | B38: 2025-12 | C38: 45968 | D38: =TEXT(C38,"YYYY-MM") -> 2025-11 | E38: ビックロ ビックカメラ新宿東口 | F38: 消耗品費・備品 | G38: 9050
A39: AMEX(Marriott Bonvoy) | B39: 2025-12 | C39: 45969 | D39: =TEXT(C39,"YYYY-MM") -> 2025-11 | E39: DAILY COFFEE STAND | F39: 飲食費 | G39: 1010 | H39: カフェ
A40: AMEX(Marriott Bonvoy) | B40: 2025-12 | C40: 45969 | D40: =TEXT(C40,"YYYY-MM") -> 2025-11 | E40: eggslut 新宿サザンテラス | F40: 飲食費 | G40: 1507
A41: AMEX(Marriott Bonvoy) | B41: 2025-12 | C41: 45969 | D41: =TEXT(C41,"YYYY-MM") -> 2025-11 | E41: GOアプリ(乗車料金) | F41: 旅費交通費 | G41: 2000
A42: AMEX(Marriott Bonvoy) | B42: 2025-12 | C42: 45970 | D42: =TEXT(C42,"YYYY-MM") -> 2025-11 | E42: YouTube Premium | F42: サブスク・ソフトウェア | G42: 1280
A43: AMEX(Marriott Bonvoy) | B43: 2025-12 | C43: 45971 | D43: =TEXT(C43,"YYYY-MM") -> 2025-11 | E43: 鷹丸鮮魚店4号店 | F43: 飲食費 | G43: 1380
A44: AMEX(Marriott Bonvoy) | B44: 2025-12 | C44: 45972 | D44: =TEXT(C44,"YYYY-MM") -> 2025-11 | E44: McAfee | F44: サブスク・ソフトウェア | G44: 12980 | H44: セキュリティ年額
A45: AMEX(Marriott Bonvoy) | B45: 2025-12 | C45: 45972 | D45: =TEXT(C45,"YYYY-MM") -> 2025-11 | E45: アマゾンサービシーズ | F45: サブスク・ソフトウェア | G45: 218
A46: AMEX(Marriott Bonvoy) | B46: 2025-12 | C46: 45972 | D46: =TEXT(C46,"YYYY-MM") -> 2025-11 | E46: スターバックス | F46: 飲食費 | G46: 1030 | H46: カフェ
A47: AMEX(Marriott Bonvoy) | B47: 2025-12 | C47: 45973 | D47: =TEXT(C47,"YYYY-MM") -> 2025-11 | E47: Apple iTunes Store | F47: サブスク・ソフトウェア | G47: 4550
A48: AMEX(Marriott Bonvoy) | B48: 2025-12 | C48: 45973 | D48: =TEXT(C48,"YYYY-MM") -> 2025-11 | E48: PAYPAL *ADVANCE STD(ACCOUNTING) | F48: 外注費 | G48: 50000 | H48: 経理代行
A49: AMEX(Marriott Bonvoy) | B49: 2025-12 | C49: 45973 | D49: =TEXT(C49,"YYYY-MM") -> 2025-11 | E49: 無印良品 | F49: 消耗品費・備品 | G49: 3260
A50: AMEX(Marriott Bonvoy) | B50: 2025-12 | C50: 45973 | D50: =TEXT(C50,"YYYY-MM") -> 2025-11 | E50: ビックロ ビックカメラ新宿東口 | F50: 消耗品費・備品 | G50: 1980
A51: AMEX(Marriott Bonvoy) | B51: 2025-12 | C51: 45973 | D51: =TEXT(C51,"YYYY-MM") -> 2025-11 | E51: システム利用料(eLTAX) | F51: 租税公課 | G51: 4000 | H51: カード納付手数料
A52: AMEX(Marriott Bonvoy) | B52: 2025-12 | C52: 45973 | D52: =TEXT(C52,"YYYY-MM") -> 2025-11 | E52: 地方税共同機構(eLTAX) | F52: 租税公課 | G52: 488200 | H52: 住民税等
A53: AMEX(Marriott Bonvoy) | B53: 2025-12 | C53: 45973 | D53: =TEXT(C53,"YYYY-MM") -> 2025-11 | E53: 源泉所得税及復興特別所得税 | F53: 租税公課 | G53: 861141
A54: AMEX(Marriott Bonvoy) | B54: 2025-12 | C54: 45974 | D54: =TEXT(C54,"YYYY-MM") -> 2025-11 | E54: PAYPAL *ADVANCE STD(ACCOUNTING) | F54: 外注費 | G54: 27500 | H54: 経理代行
A55: AMEX(Marriott Bonvoy) | B55: 2025-12 | C55: 45974 | D55: =TEXT(C55,"YYYY-MM") -> 2025-11 | E55: 鷹丸鮮魚店4号店 | F55: 飲食費 | G55: 1380
A56: AMEX(Marriott Bonvoy) | B56: 2025-12 | C56: 45974 | D56: =TEXT(C56,"YYYY-MM") -> 2025-11 | E56: 楽天ペイ Respia | F56: 美容 | G56: 5005 | H56: 美容院/エステ
A57: AMEX(Marriott Bonvoy) | B57: 2025-12 | C57: 45975 | D57: =TEXT(C57,"YYYY-MM") -> 2025-11 | E57: 鷹丸鮮魚店4号店 | F57: 飲食費 | G57: 1980
A58: AMEX(Marriott Bonvoy) | B58: 2025-12 | C58: 45975 | D58: =TEXT(C58,"YYYY-MM") -> 2025-11 | E58: スターバックス | F58: 飲食費 | G58: 440 | H58: カフェ
A59: AMEX(Marriott Bonvoy) | B59: 2025-12 | C59: 45977 | D59: =TEXT(C59,"YYYY-MM") -> 2025-11 | E59: 野方餃子/Air | F59: 飲食費 | G59: 3399
A60: AMEX(Marriott Bonvoy) | B60: 2025-12 | C60: 45978 | D60: =TEXT(C60,"YYYY-MM") -> 2025-11 | E60: 鷹丸鮮魚店4号店 | F60: 飲食費 | G60: 1380
A61: AMEX(Marriott Bonvoy) | B61: 2025-12 | C61: 45978 | D61: =TEXT(C61,"YYYY-MM") -> 2025-11 | E61: リブクオリティハブ(名古屋) | F61: 新聞図書費 | G61: 5000 | H61: 購読料
A62: AMEX(Marriott Bonvoy) | B62: 2025-12 | C62: 45979 | D62: =TEXT(C62,"YYYY-MM") -> 2025-11 | E62: ヒモノ照ラス(名古屋) | F62: 飲食費 | G62: 1958
A63: AMEX(Marriott Bonvoy) | B63: 2025-12 | C63: 45979 | D63: =TEXT(C63,"YYYY-MM") -> 2025-11 | E63: 名古屋駅店舗 | F63: 雑費・その他 | G63: 3260
A64: AMEX(Marriott Bonvoy) | B64: 2025-12 | C64: 45979 | D64: =TEXT(C64,"YYYY-MM") -> 2025-11 | E64: エクスプレス予約 | F64: 旅費交通費 | G64: 10880 | H64: 新幹線
A65: AMEX(Marriott Bonvoy) | B65: 2025-12 | C65: 45979 | D65: =TEXT(C65,"YYYY-MM") -> 2025-11 | E65: エクスプレス予約 | F65: 旅費交通費 | G65: 10880 | H65: 新幹線
A66: AMEX(Marriott Bonvoy) | B66: 2025-12 | C66: 45979 | D66: =TEXT(C66,"YYYY-MM") -> 2025-11 | E66: つばめ交通 | F66: 旅費交通費 | G66: 1800 | H66: タクシー
A67: AMEX(Marriott Bonvoy) | B67: 2025-12 | C67: 45979 | D67: =TEXT(C67,"YYYY-MM") -> 2025-11 | E67: GOアプリ(乗車料金) | F67: 旅費交通費 | G67: 1800
A68: AMEX(Marriott Bonvoy) | B68: 2025-12 | C68: 45980 | D68: =TEXT(C68,"YYYY-MM") -> 2025-11 | E68: 鷹丸鮮魚店4号店 | F68: 飲食費 | G68: 1380
A69: AMEX(Marriott Bonvoy) | B69: 2025-12 | C69: 45981 | D69: =TEXT(C69,"YYYY-MM") -> 2025-11 | E69: 名古屋マリオットアソシアホテル | F69: 旅費交通費 | G69: 3900 | H69: 宿泊
A70: AMEX(Marriott Bonvoy) | B70: 2025-12 | C70: 45981 | D70: =TEXT(C70,"YYYY-MM") -> 2025-11 | E70: エクスプレス予約 | F70: 旅費交通費 | G70: 10880 | H70: 新幹線
A71: AMEX(Marriott Bonvoy) | B71: 2025-12 | C71: 45981 | D71: =TEXT(C71,"YYYY-MM") -> 2025-11 | E71: エクスプレス予約 | F71: 旅費交通費 | G71: 14540 | H71: 新幹線
A72: AMEX(Marriott Bonvoy) | B72: 2025-12 | C72: 45982 | D72: =TEXT(C72,"YYYY-MM") -> 2025-11 | E72: 鷹丸鮮魚店4号店 | F72: 飲食費 | G72: 1980
A73: AMEX(Marriott Bonvoy) | B73: 2025-12 | C73: 45982 | D73: =TEXT(C73,"YYYY-MM") -> 2025-11 | E73: アマゾンサービシーズ | F73: サブスク・ソフトウェア | G73: 1352
A74: AMEX(Marriott Bonvoy) | B74: 2025-12 | C74: 45982 | D74: =TEXT(C74,"YYYY-MM") -> 2025-11 | E74: 大木TAXI | F74: 旅費交通費 | G74: 1200 | H74: タクシー
A75: AMEX(Marriott Bonvoy) | B75: 2025-12 | C75: 45984 | D75: =TEXT(C75,"YYYY-MM") -> 2025-11 | E75: Apple iTunes Store | F75: サブスク・ソフトウェア | G75: 740
A76: AMEX(Marriott Bonvoy) | B76: 2025-12 | C76: 45985 | D76: =TEXT(C76,"YYYY-MM") -> 2025-11 | E76: Apple iTunes Store | F76: サブスク・ソフトウェア | G76: 3400
A77: AMEX(Marriott Bonvoy) | B77: 2025-12 | C77: 45985 | D77: =TEXT(C77,"YYYY-MM") -> 2025-11 | E77: アマゾン | F77: 消耗品費・備品 | G77: 2420
A78: AMEX(Marriott Bonvoy) | B78: 2025-12 | C78: 45986 | D78: =TEXT(C78,"YYYY-MM") -> 2025-11 | E78: ヒモノ照ラス(名古屋) | F78: 飲食費 | G78: 2068
A79: AMEX(Marriott Bonvoy) | B79: 2025-12 | C79: 45986 | D79: =TEXT(C79,"YYYY-MM") -> 2025-11 | E79: 名古屋駅店舗 | F79: 雑費・その他 | G79: 2820
A80: AMEX(Marriott Bonvoy) | B80: 2025-12 | C80: 45986 | D80: =TEXT(C80,"YYYY-MM") -> 2025-11 | E80: エクスプレス予約 | F80: 旅費交通費 | G80: 10880 | H80: 新幹線
A81: AMEX(Marriott Bonvoy) | B81: 2025-12 | C81: 45986 | D81: =TEXT(C81,"YYYY-MM") -> 2025-11 | E81: エクスプレス予約 | F81: 旅費交通費 | G81: 10880 | H81: 新幹線
A82: AMEX(Marriott Bonvoy) | B82: 2025-12 | C82: 45986 | D82: =TEXT(C82,"YYYY-MM") -> 2025-11 | E82: アフターコールナビ | F82: 外注費 | G82: 137293 | H82: 電話代行
A83: AMEX(Marriott Bonvoy) | B83: 2025-12 | C83: 45987 | D83: =TEXT(C83,"YYYY-MM") -> 2025-11 | E83: 木曽路 環七小竹町店 | F83: 飲食費 | G83: 7095
A84: AMEX(Marriott Bonvoy) | B84: 2025-12 | C84: 45987 | D84: =TEXT(C84,"YYYY-MM") -> 2025-11 | E84: アドビ | F84: サブスク・ソフトウェア | G84: 4980
A85: AMEX(Marriott Bonvoy) | B85: 2025-12 | C85: 45987 | D85: =TEXT(C85,"YYYY-MM") -> 2025-11 | E85: 03Plus | F85: 通信費 | G85: 3815 | H85: クラウド電話
A86: AMEX(Marriott Bonvoy) | B86: 2025-12 | C86: 45987 | D86: =TEXT(C86,"YYYY-MM") -> 2025-11 | E86: タイムズ昭和医科大学歯科病院 | F86: 車両費 | G86: 600 | H86: 駐車場
A87: AMEX(Marriott Bonvoy) | B87: 2025-12 | C87: 45988 | D87: =TEXT(C87,"YYYY-MM") -> 2025-11 | E87: ヒモノ照ラス(名古屋) | F87: 飲食費 | G87: 1848
A88: AMEX(Marriott Bonvoy) | B88: 2025-12 | C88: 45988 | D88: =TEXT(C88,"YYYY-MM") -> 2025-11 | E88: 名古屋マリオットアソシアホテル | F88: 旅費交通費 | G88: 2200 | H88: 宿泊
A89: AMEX(Marriott Bonvoy) | B89: 2025-12 | C89: 45988 | D89: =TEXT(C89,"YYYY-MM") -> 2025-11 | E89: エクスプレス予約 | F89: 旅費交通費 | G89: 10880 | H89: 新幹線
A90: AMEX(Marriott Bonvoy) | B90: 2025-12 | C90: 45988 | D90: =TEXT(C90,"YYYY-MM") -> 2025-11 | E90: エクスプレス予約 | F90: 旅費交通費 | G90: 10880 | H90: 新幹線
A91: AMEX(Marriott Bonvoy) | B91: 2025-12 | C91: 45988 | D91: =TEXT(C91,"YYYY-MM") -> 2025-11 | E91: つばめ交通 | F91: 旅費交通費 | G91: 1600 | H91: タクシー
A92: AMEX(Marriott Bonvoy) | B92: 2025-12 | C92: 45989 | D92: =TEXT(C92,"YYYY-MM") -> 2025-11 | E92: 鷹丸鮮魚店4号店 | F92: 飲食費 | G92: 1380
A93: AMEX(Marriott Bonvoy) | B93: 2025-12 | C93: 45990 | D93: =TEXT(C93,"YYYY-MM") -> 2025-11 | E93: すし銚子丸 豊玉南店 | F93: 飲食費 | G93: 11991
A94: AMEX(Marriott Bonvoy) | B94: 2025-12 | C94: 45991 | D94: =TEXT(C94,"YYYY-MM") -> 2025-11 | E94: バランス大家サロン | F94: 諸会費・コミュニティ | G94: 22000 | H94: 月額サロン
A95: AMEX(Marriott Bonvoy) | B95: 2025-12 | C95: 45992 | D95: =TEXT(C95,"YYYY-MM") -> 2025-12 | E95: MD(MDISM) SERVICE | F95: サブスク・ソフトウェア | G95: 5478 | H95: 内容要確認
A96: AMEX(Marriott Bonvoy) | B96: 2025-12 | C96: 45992 | D96: =TEXT(C96,"YYYY-MM") -> 2025-12 | E96: 鷹丸鮮魚店4号店 | F96: 飲食費 | G96: 1380
A97: AMEX(Marriott Bonvoy) | B97: 2025-12 | C97: 45993 | D97: =TEXT(C97,"YYYY-MM") -> 2025-12 | E97: 鷹丸鮮魚店4号店 | F97: 飲食費 | G97: 1980
A98: AMEX(Marriott Bonvoy) | B98: 2025-12 | C98: 45993 | D98: =TEXT(C98,"YYYY-MM") -> 2025-12 | E98: ビックロ ビックカメラ新宿東口 | F98: 消耗品費・備品 | G98: 9890
A99: AMEX(Marriott Bonvoy) | B99: 2025-12 | C99: 45994 | D99: =TEXT(C99,"YYYY-MM") -> 2025-12 | E99: アマゾンJPマーケットプレイス | F99: 消耗品費・備品 | G99: 4436
A100: AMEX(Marriott Bonvoy) | B100: 2026-01 | C100: 45989 | D100: =TEXT(C100,"YYYY-MM") -> 2025-11 | E100: 東邦ガス(11月分) | F100: 水道光熱費 | G100: 2441
...

Sheet 科目別集計
A1: 勘定科目別 × 利用月別 集計(2枚のカード合算・単位:円)
A2: 対象期間: 2025年10月末〜2026年8月上旬利用分(AMEX 2025/12〜2026/8締め、ANA VISA 2026/2〜2026/8支払分)
A4: 勘定科目 | B4: 2025-10 | C4: 2025-11 | D4: 2025-12 | E4: 2026-01 | F4: 2026-02 | G4: 2026-03 | H4: 2026-04 | I4: 2026-05 | J4: 2026-06 | K4: 2026-07 | L4: 2026-08 | M4: 合計 | N4: 構成比
A5: 租税公課 | B5: =SUMIFS(全明細!$G$2:$G$975,全明細!$F$2:$F$975,$A5,全明細!$D$2:$D$975,B$4) -> 0 | C5: =SUMIFS(全明細!$G$2:$G$975,全明細!$F$2:$F$975,$A5,全明細!$D$2:$D$975,C$4) -> 1353341 | D5: =SUMIFS(全明細!$G$2:$G$975,全明細!$F$2:$F$975,$A5,全明細!$D$2:$D$975,D$4) -> 492200 | E5: =SUMIFS(全明細!$G$2:$G$975,全明細!$F$2:$F$975,$A5,全明細!$D$2:$D$975,E$4) -> 943741 | F5: =SUMIFS(全明細!$G$2:$G$975,全明細!$F$2:$F$975,$A5,全明細!$D$2:$D$975,F$4) -> 878054 | G5: =SUMIFS(全明細!$G$2:$G$975,全明細!$F$2:$F$975,$A5,全明細!$D$2:$D$975,G$4) -> 9010409 | H5: =SUMIFS(全明細!$G$2:$G$975,全明細!$F$2:$F$975,$A5,全明細!$D$2:$D$975,H$4) -> 0 | I5: =SUMIFS(全明細!$G$2:$G$975,全明細!$F$2:$F$975,$A5,全明細!$D$2:$D$975,I$4) -> 3473800 | ... L5: =SUMIFS(全明細!$G$2:$G$975,全明細!$F$2:$F$975,$A5,全明細!$D$2:$D$975,L$4) -> 0 | M5: =SUM(B5:L5) -> 17054186 | N5: =IF(M$22=0,0,M5/M$22) -> 0.57050762
A6: 外注費 | B6: =SUMIFS(全明細!$G$2:$G$975,全明細!$F$2:$F$975,$A6,全明細!$D$2:$D$975,B$4) -> 0 | C6: =SUMIFS(全明細!$G$2:$G$975,全明細!$F$2:$F$975,$A6,全明細!$D$2:$D$975,C$4) -> 214793 | D6: =SUMIFS(全明細!$G$2:$G$975,全明細!$F$2:$F$975,$A6,全明細!$D$2:$D$975,D$4) -> 277880 | E6: =SUMIFS(全明細!$G$2:$G$975,全明細!$F$2:$F$975,$A6,全明細!$D$2:$D$975,E$4) -> 278146 | F6: =SUMIFS(全明細!$G$2:$G$975,全明細!$F$2:$F$975,$A6,全明細!$D$2:$D$975,F$4) -> 205458 | G6: =SUMIFS(全明細!$G$2:$G$975,全明細!$F$2:$F$975,$A6,全明細!$D$2:$D$975,G$4) -> 163995 | H6: =SUMIFS(全明細!$G$2:$G$975,全明細!$F$2:$F$975,$A6,全明細!$D$2:$D$975,H$4) -> 131727 | I6: =SUMIFS(全明細!$G$2:$G$975,全明細!$F$2:$F$975,$A6,全明細!$D$2:$D$975,I$4) -> 302309 | ... L6: =SUMIFS(全明細!$G$2:$G$975,全明細!$F$2:$F$975,$A6,全明細!$D$2:$D$975,L$4) -> 30000 | M6: =SUM(B6:L6) -> 2194671 | N6: =IF(M$22=0,0,M6/M$22) -> 0.073417549
A7: 消耗品費・備品 | B7: =SUMIFS(全明細!$G$2:$G$975,全明細!$F$2:$F$975,$A7,全明細!$D$2:$D$975,B$4) -> 0 | C7: =SUMIFS(全明細!$G$2:$G$975,全明細!$F$2:$F$975,$A7,全明細!$D$2:$D$975,C$4) -> 93333 | D7: =SUMIFS(全明細!$G$2:$G$975,全明細!$F$2:$F$975,$A7,全明細!$D$2:$D$975,D$4) -> 215342 | E7: =SUMIFS(全明細!$G$2:$G$975,全明細!$F$2:$F$975,$A7,全明細!$D$2:$D$975,E$4) -> 1366700 | F7: =SUMIFS(全明細!$G$2:$G$975,全明細!$F$2:$F$975,$A7,全明細!$D$2:$D$975,F$4) -> 932351 | G7: =SUMIFS(全明細!$G$2:$G$975,全明細!$F$2:$F$975,$A7,全明細!$D$2:$D$975,G$4) -> 761052 | H7: =SUMIFS(全明細!$G$2:$G$975,全明細!$F$2:$F$975,$A7,全明細!$D$2:$D$975,H$4) -> 249824 | I7: =SUMIFS(全明細!$G$2:$G$975,全明細!$F$2:$F$975,$A7,全明細!$D$2:$D$975,I$4) -> 131502 | ... L7: =SUMIFS(全明細!$G$2:$G$975,全明細!$F$2:$F$975,$A7,全明細!$D$2:$D$975,L$4) -> 0 | M7: =SUM(B7:L7) -> 4157753 | N7: =IF(M$22=0,0,M7/M$22) -> 0.13908783
A8: 旅費交通費 | B8: =SUMIFS(全明細!$G$2:$G$975,全明細!$F$2:$F$975,$A8,全明細!$D$2:$D$975,B$4) -> 4700 | C8: =SUMIFS(全明細!$G$2:$G$975,全明細!$F$2:$F$975,$A8,全明細!$D$2:$D$975,C$4) -> 148720 | D8: =SUMIFS(全明細!$G$2:$G$975,全明細!$F$2:$F$975,$A8,全明細!$D$2:$D$975,D$4) -> 77440 | E8: =SUMIFS(全明細!$G$2:$G$975,全明細!$F$2:$F$975,$A8,全明細!$D$2:$D$975,E$4) -> 31690 | F8: =SUMIFS(全明細!$G$2:$G$975,全明細!$F$2:$F$975,$A8,全明細!$D$2:$D$975,F$4) -> 66560 | G8: =SUMIFS(全明細!$G$2:$G$975,全明細!$F$2:$F$975,$A8,全明細!$D$2:$D$975,G$4) -> 114705 | H8: =SUMIFS(全明細!$G$2:$G$975,全明細!$F$2:$F$975,$A8,全明細!$D$2:$D$975,H$4) -> 129064 | I8: =SUMIFS(全明細!$G$2:$G$975,全明細!$F$2:$F$975,$A8,全明細!$D$2:$D$975,I$4) -> 300004 | ... L8: =SUMIFS(全明細!$G$2:$G$975,全明細!$F$2:$F$975,$A8,全明細!$D$2:$D$975,L$4) -> 0 | M8: =SUM(B8:L8) -> 1398764 | N8: =IF(M$22=0,0,M8/M$22) -> 0.046792355
A9: 車両費 | B9: =SUMIFS(全明細!$G$2:$G$975,全明細!$F$2:$F$975,$A9,全明細!$D$2:$D$975,B$4) -> 0 | C9: =SUMIFS(全明細!$G$2:$G$975,全明細!$F$2:$F$975,$A9,全明細!$D$2:$D$975,C$4) -> 13035 | D9: =SUMIFS(全明細!$G$2:$G$975,全明細!$F$2:$F$975,$A9,全明細!$D$2:$D$975,D$4) -> 10189 | E9: =SUMIFS(全明細!$G$2:$G$975,全明細!$F$2:$F$975,$A9,全明細!$D$2:$D$975,E$4) -> 32055 | F9: =SUMIFS(全明細!$G$2:$G$975,全明細!$F$2:$F$975,$A9,全明細!$D$2:$D$975,F$4) -> 15093 | G9: =SUMIFS(全明細!$G$2:$G$975,全明細!$F$2:$F$975,$A9,全明細!$D$2:$D$975,G$4) -> 329194 | H9: =SUMIFS(全明細!$G$2:$G$975,全明細!$F$2:$F$975,$A9,全明細!$D$2:$D$975,H$4) -> 9920 | I9: =SUMIFS(全明細!$G$2:$G$975,全明細!$F$2:$F$975,$A9,全明細!$D$2:$D$975,I$4) -> 27850 | ... L9: =SUMIFS(全明細!$G$2:$G$975,全明細!$F$2:$F$975,$A9,全明細!$D$2:$D$975,L$4) -> 0 | M9: =SUM(B9:L9) -> 735436 | N9: =IF(M$22=0,0,M9/M$22) -> 0.024602279
A10: 飲食費 | B10: =SUMIFS(全明細!$G$2:$G$975,全明細!$F$2:$F$975,$A10,全明細!$D$2:$D$975,B$4) -> 0 | C10: =SUMIFS(全明細!$G$2:$G$975,全明細!$F$2:$F$975,$A10,全明細!$D$2:$D$975,C$4) -> 65922 | D10: =SUMIFS(全明細!$G$2:$G$975,全明細!$F$2:$F$975,$A10,全明細!$D$2:$D$975,D$4) -> 82644 | E10: =SUMIFS(全明細!$G$2:$G$975,全明細!$F$2:$F$975,$A10,全明細!$D$2:$D$975,E$4) -> 59879 | F10: =SUMIFS(全明細!$G$2:$G$975,全明細!$F$2:$F$975,$A10,全明細!$D$2:$D$975,F$4) -> 79273 | G10: =SUMIFS(全明細!$G$2:$G$975,全明細!$F$2:$F$975,$A10,全明細!$D$2:$D$975,G$4) -> 114759 | H10: =SUMIFS(全明細!$G$2:$G$975,全明細!$F$2:$F$975,$A10,全明細!$D$2:$D$975,H$4) -> 93846 | I10: =SUMIFS(全明細!$G$2:$G$975,全明細!$F$2:$F$975,$A10,全明細!$D$2:$D$975,I$4) -> 238677 | ... L10: =SUMIFS(全明細!$G$2:$G$975,全明細!$F$2:$F$975,$A10,全明細!$D$2:$D$975,L$4) -> 0 | M10: =SUM(B10:L10) -> 794577 | N10: =IF(M$22=0,0,M10/M$22) -> 0.026580702
A11: サブスク・ソフトウェア | B11: =SUMIFS(全明細!$G$2:$G$975,全明細!$F$2:$F$975,$A11,全明細!$D$2:$D$975,B$4) -> 0 | C11: =SUMIFS(全明細!$G$2:$G$975,全明細!$F$2:$F$975,$A11,全明細!$D$2:$D$975,C$4) -> 33900 | D11: =SUMIFS(全明細!$G$2:$G$975,全明細!$F$2:$F$975,$A11,全明細!$D$2:$D$975,D$4) -> 21028 | E11: =SUMIFS(全明細!$G$2:$G$975,全明細!$F$2:$F$975,$A11,全明細!$D$2:$D$975,E$4) -> 20278 | F11: =SUMIFS(全明細!$G$2:$G$975,全明細!$F$2:$F$975,$A11,全明細!$D$2:$D$975,F$4) -> 15780 | G11: =SUMIFS(全明細!$G$2:$G$975,全明細!$F$2:$F$975,$A11,全明細!$D$2:$D$975,G$4) -> 121050 | H11: =SUMIFS(全明細!$G$2:$G$975,全明細!$F$2:$F$975,$A11,全明細!$D$2:$D$975,H$4) -> 26613 | I11: =SUMIFS(全明細!$G$2:$G$975,全明細!$F$2:$F$975,$A11,全明細!$D$2:$D$975,I$4) -> 60181 | ... L11: =SUMIFS(全明細!$G$2:$G$975,全明細!$F$2:$F$975,$A11,全明細!$D$2:$D$975,L$4) -> 1580 | M11: =SUM(B11:L11) -> 412534 | N11: =IF(M$22=0,0,M11/M$22) -> 0.013800353
A12: 諸会費・コミュニティ | B12: =SUMIFS(全明細!$G$2:$G$975,全明細!$F$2:$F$975,$A12,全明細!$D$2:$D$975,B$4) -> 0 | C12: =SUMIFS(全明細!$G$2:$G$975,全明細!$F$2:$F$975,$A12,全明細!$D$2:$D$975,C$4) -> 32780 | D12: =SUMIFS(全明細!$G$2:$G$975,全明細!$F$2:$F$975,$A12,全明細!$D$2:$D$975,D$4) -> 32780 | E12: =SUMIFS(全明細!$G$2:$G$975,全明細!$F$2:$F$975,$A12,全明細!$D$2:$D$975,E$4) -> 130680 | F12: =SUMIFS(全明細!$G$2:$G$975,全明細!$F$2:$F$975,$A12,全明細!$D$2:$D$975,F$4) -> 49280 | G12: =SUMIFS(全明細!$G$2:$G$975,全明細!$F$2:$F$975,$A12,全明細!$D$2:$D$975,G$4) -> 49280 | H12: =SUMIFS(全明細!$G$2:$G$975,全明細!$F$2:$F$975,$A12,全明細!$D$2:$D$975,H$4) -> 32780 | I12: =SUMIFS(全明細!$G$2:$G$975,全明細!$F$2:$F$975,$A12,全明細!$D$2:$D$975,I$4) -> 49280 | ... L12: =SUMIFS(全明細!$G$2:$G$975,全明細!$F$2:$F$975,$A12,全明細!$D$2:$D$975,L$4) -> 0 | M12: =SUM(B12:L12) -> 432740 | N12: =IF(M$22=0,0,M12/M$22) -> 0.014476297
A13: 通信費 | B13: =SUMIFS(全明細!$G$2:$G$975,全明細!$F$2:$F$975,$A13,全明細!$D$2:$D$975,B$4) -> 12169 | C13: =SUMIFS(全明細!$G$2:$G$975,全明細!$F$2:$F$975,$A13,全明細!$D$2:$D$975,C$4) -> 20874 | D13: =SUMIFS(全明細!$G$2:$G$975,全明細!$F$2:$F$975,$A13,全明細!$D$2:$D$975,D$4) -> 20792 | E13: =SUMIFS(全明細!$G$2:$G$975,全明細!$F$2:$F$975,$A13,全明細!$D$2:$D$975,E$4) -> 28335 | F13: =SUMIFS(全明細!$G$2:$G$975,全明細!$F$2:$F$975,$A13,全明細!$D$2:$D$975,F$4) -> 21501 | G13: =SUMIFS(全明細!$G$2:$G$975,全明細!$F$2:$F$975,$A13,全明細!$D$2:$D$975,G$4) -> 17559 | H13: =SUMIFS(全明細!$G$2:$G$975,全明細!$F$2:$F$975,$A13,全明細!$D$2:$D$975,H$4) -> 13443 | I13: =SUMIFS(全明細!$G$2:$G$975,全明細!$F$2:$F$975,$A13,全明細!$D$2:$D$975,I$4) -> 20798 | ... L13: =SUMIFS(全明細!$G$2:$G$975,全明細!$F$2:$F$975,$A13,全明細!$D$2:$D$975,L$4) -> 0 | M13: =SUM(B13:L13) -> 171253 | N13: =IF(M$22=0,0,M13/M$22) -> 0.0057288657
A14: 水道光熱費 | B14: =SUMIFS(全明細!$G$2:$G$975,全明細!$F$2:$F$975,$A14,全明細!$D$2:$D$975,B$4) -> 2408 | C14: =SUMIFS(全明細!$G$2:$G$975,全明細!$F$2:$F$975,$A14,全明細!$D$2:$D$975,C$4) -> 6609 | D14: =SUMIFS(全明細!$G$2:$G$975,全明細!$F$2:$F$975,$A14,全明細!$D$2:$D$975,D$4) -> 2685 | E14: =SUMIFS(全明細!$G$2:$G$975,全明細!$F$2:$F$975,$A14,全明細!$D$2:$D$975,E$4) -> 2838 | F14: =SUMIFS(全明細!$G$2:$G$975,全明細!$F$2:$F$975,$A14,全明細!$D$2:$D$975,F$4) -> 6182 | G14: =SUMIFS(全明細!$G$2:$G$975,全明細!$F$2:$F$975,$A14,全明細!$D$2:$D$975,G$4) -> 9792 | H14: =SUMIFS(全明細!$G$2:$G$975,全明細!$F$2:$F$975,$A14,全明細!$D$2:$D$975,H$4) -> 9561 | I14: =SUMIFS(全明細!$G$2:$G$975,全明細!$F$2:$F$975,$A14,全明細!$D$2:$D$975,I$4) -> 15973 | ... L14: =SUMIFS(全明細!$G$2:$G$975,全明細!$F$2:$F$975,$A14,全明細!$D$2:$D$975,L$4) -> 0 | M14: =SUM(B14:L14) -> 81685 | N14: =IF(M$22=0,0,M14/M$22) -> 0.0027325793
A15: 研修・セミナー | B15: =SUMIFS(全明細!$G$2:$G$975,全明細!$F$2:$F$975,$A15,全明細!$D$2:$D$975,B$4) -> 0 | C15: =SUMIFS(全明細!$G$2:$G$975,全明細!$F$2:$F$975,$A15,全明細!$D$2:$D$975,C$4) -> 0 | D15: =SUMIFS(全明細!$G$2:$G$975,全明細!$F$2:$F$975,$A15,全明細!$D$2:$D$975,D$4) -> 0 | E15: =SUMIFS(全明細!$G$2:$G$975,全明細!$F$2:$F$975,$A15,全明細!$D$2:$D$975,E$4) -> 0 | F15: =SUMIFS(全明細!$G$2:$G$975,全明細!$F$2:$F$975,$A15,全明細!$D$2:$D$975,F$4) -> 0 | G15: =SUMIFS(全明細!$G$2:$G$975,全明細!$F$2:$F$975,$A15,全明細!$D$2:$D$975,G$4) -> 0 | H15: =SUMIFS(全明細!$G$2:$G$975,全明細!$F$2:$F$975,$A15,全明細!$D$2:$D$975,H$4) -> 77000 | I15: =SUMIFS(全明細!$G$2:$G$975,全明細!$F$2:$F$975,$A15,全明細!$D$2:$D$975,I$4) -> 33000 | ... L15: =SUMIFS(全明細!$G$2:$G$975,全明細!$F$2:$F$975,$A15,全明細!$D$2:$D$975,L$4) -> 0 | M15: =SUM(B15:L15) -> 118000 | N15: =IF(M$22=0,0,M15/M$22) -> 0.003947412
A16: 新聞図書費 | B16: =SUMIFS(全明細!$G$2:$G$975,全明細!$F$2:$F$975,$A16,全明細!$D$2:$D$975,B$4) -> 0 | C16: =SUMIFS(全明細!$G$2:$G$975,全明細!$F$2:$F$975,$A16,全明細!$D$2:$D$975,C$4) -> 6760 | D16: =SUMIFS(全明細!$G$2:$G$975,全明細!$F$2:$F$975,$A16,全明細!$D$2:$D$975,D$4) -> 0 | E16: =SUMIFS(全明細!$G$2:$G$975,全明細!$F$2:$F$975,$A16,全明細!$D$2:$D$975,E$4) -> 7390 | F16: =SUMIFS(全明細!$G$2:$G$975,全明細!$F$2:$F$975,$A16,全明細!$D$2:$D$975,F$4) -> 5140 | G16: =SUMIFS(全明細!$G$2:$G$975,全明細!$F$2:$F$975,$A16,全明細!$D$2:$D$975,G$4) -> 4500 | H16: =SUMIFS(全明細!$G$2:$G$975,全明細!$F$2:$F$975,$A16,全明細!$D$2:$D$975,H$4) -> 1500 | I16: =SUMIFS(全明細!$G$2:$G$975,全明細!$F$2:$F$975,$A16,全明細!$D$2:$D$975,I$4) -> 0 | ... L16: =SUMIFS(全明細!$G$2:$G$975,全明細!$F$2:$F$975,$A16,全明細!$D$2:$D$975,L$4) -> 0 | M16: =SUM(B16:L16) -> 25290 | N16: =IF(M$22=0,0,M16/M$22) -> 0.00084601738
... A21: 不明・要確認 | B21: =SUMIFS(全明細!$G$2:$G$975,全明細!$F$2:$F$975,$A21,全明細!$D$2:$D$975,B$4) -> 0 | C21: =SUMIFS(全明細!$G$2:$G$975,全明細!$F$2:$F$975,$A21,全明細!$D$2:$D$975,C$4) -> 0 | D21: =SUMIFS(全明細!$G$2:$G$975,全明細!$F$2:$F$975,$A21,全明細!$D$2:$D$975,D$4) -> 0 | E21: =SUMIFS(全明細!$G$2:$G$975,全明細!$F$2:$F$975,$A21,全明細!$D$2:$D$975,E$4) -> 0 | F21: =SUMIFS(全明細!$G$2:$G$975,全明細!$F$2:$F$975,$A21,全明細!$D$2:$D$975,F$4) -> 0 | G21: =SUMIFS(全明細!$G$2:$G$975,全明細!$F$2:$F$975,$A21,全明細!$D$2:$D$975,G$4) -> 0 | H21: =SUMIFS(全明細!$G$2:$G$975,全明細!$F$2:$F$975,$A21,全明細!$D$2:$D$975,H$4) -> 1350511 | I21: =SUMIFS(全明細!$G$2:$G$975,全明細!$F$2:$F$975,$A21,全明細!$D$2:$D$975,I$4) -> 0 | ... L21: =SUMIFS(全明細!$G$2:$G$975,全明細!$F$2:$F$975,$A21,全明細!$D$2:$D$975,L$4) -> 0 | M21: =SUM(B21:L21) -> 1350511 | N21: =IF(M$22=0,0,M21/M$22) -> 0.045178164
A22: 合計 | B22: =SUM(B5:B21) -> 19277 | C22: =SUM(C5:C21) -> 2017892 | D22: =SUM(D5:D21) -> 1300106 | E22: =SUM(E5:E21) -> 3025275 | F22: =SUM(F5:F21) -> 2405462 | G22: =SUM(G5:G21) -> 10866716 | H22: =SUM(H5:H21) -> 2229663 | I22: =SUM(I5:I21) -> 4819015 | ... M22: =SUM(M5:M21) -> 29893003
A23: (参考)租税公課を除く合計 | B23: =B22-B5 -> 19277 | C23: =C22-C5 -> 664551 | D23: =D22-D5 -> 807906 | E23: =E22-E5 -> 2081534 | F23: =F22-F5 -> 1527408 | G23: =G22-G5 -> 1856307 | H23: =H22-H5 -> 2229663 | I23: =I22-I5 -> 1345215 | ... M23: =M22-M5 -> 12838817

Sheet 月別カード別
A1: カード別 × 利用月別 集計(単位:円)
A3: カード | B3: 2025-10 | C3: 2025-11 | D3: 2025-12 | E3: 2026-01 | F3: 2026-02 | G3: 2026-03 | H3: 2026-04 | I3: 2026-05 | J3: 2026-06 | K3: 2026-07 | L3: 2026-08 | M3: 合計
A4: AMEX(Marriott Bonvoy) | B4: =SUMIFS(全明細!$G$2:$G$975,全明細!$A$2:$A$975,$A4,全明細!$D$2:$D$975,B$3) -> 19277 | C4: =SUMIFS(全明細!$G$2:$G$975,全明細!$A$2:$A$975,$A4,全明細!$D$2:$D$975,C$3) -> 2017892 | D4: =SUMIFS(全明細!$G$2:$G$975,全明細!$A$2:$A$975,$A4,全明細!$D$2:$D$975,D$3) -> 1300106 | E4: =SUMIFS(全明細!$G$2:$G$975,全明細!$A$2:$A$975,$A4,全明細!$D$2:$D$975,E$3) -> 578540 | F4: =SUMIFS(全明細!$G$2:$G$975,全明細!$A$2:$A$975,$A4,全明細!$D$2:$D$975,F$3) -> 1263204 | G4: =SUMIFS(全明細!$G$2:$G$975,全明細!$A$2:$A$975,$A4,全明細!$D$2:$D$975,G$3) -> 3705295 | H4: =SUMIFS(全明細!$G$2:$G$975,全明細!$A$2:$A$975,$A4,全明細!$D$2:$D$975,H$3) -> 643395 | I4: =SUMIFS(全明細!$G$2:$G$975,全明細!$A$2:$A$975,$A4,全明細!$D$2:$D$975,I$3) -> 1348862 | ... L4: =SUMIFS(全明細!$G$2:$G$975,全明細!$A$2:$A$975,$A4,全明細!$D$2:$D$975,L$3) -> 31580 | M4: =SUM(B4:L4) -> 12531024
A5: ANA VISAプラチナ | B5: =SUMIFS(全明細!$G$2:$G$975,全明細!$A$2:$A$975,$A5,全明細!$D$2:$D$975,B$3) -> 0 | C5: =SUMIFS(全明細!$G$2:$G$975,全明細!$A$2:$A$975,$A5,全明細!$D$2:$D$975,C$3) -> 0 | D5: =SUMIFS(全明細!$G$2:$G$975,全明細!$A$2:$A$975,$A5,全明細!$D$2:$D$975,D$3) -> 0 | E5: =SUMIFS(全明細!$G$2:$G$975,全明細!$A$2:$A$975,$A5,全明細!$D$2:$D$975,E$3) -> 2446735 | F5: =SUMIFS(全明細!$G$2:$G$975,全明細!$A$2:$A$975,$A5,全明細!$D$2:$D$975,F$3) -> 1142258 | G5: =SUMIFS(全明細!$G$2:$G$975,全明細!$A$2:$A$975,$A5,全明細!$D$2:$D$975,G$3) -> 7161421 | H5: =SUMIFS(全明細!$G$2:$G$975,全明細!$A$2:$A$975,$A5,全明細!$D$2:$D$975,H$3) -> 1586268 | I5: =SUMIFS(全明細!$G$2:$G$975,全明細!$A$2:$A$975,$A5,全明細!$D$2:$D$975,I$3) -> 3470153 | ... L5: =SUMIFS(全明細!$G$2:$G$975,全明細!$A$2:$A$975,$A5,全明細!$D$2:$D$975,L$3) -> 0 | M5: =SUM(B5:L5) -> 17361979
A6: 合計 | B6: =SUM(B4:B5) -> 19277 | C6: =SUM(C4:C5) -> 2017892 | D6: =SUM(D4:D5) -> 1300106 | E6: =SUM(E4:E5) -> 3025275 | F6: =SUM(F4:F5) -> 2405462 | G6: =SUM(G4:G5) -> 10866716 | H6: =SUM(H4:H5) -> 2229663 | I6: =SUM(I4:I5) -> 4819015 | ... M6: =SUM(M4:M5) -> 29893003
A8: ※ ANA VISAは支払月ベースの明細のため、利用月は明細記載の利用日で集計。
A9: ※ ANA 2026/5支払分のうち1,350,511円は明細PDF2ページ目未添付のため内訳不明(全明細シート最終付近参照)。

Sheet 定期支出・サブスク
A1: 毎月発生している固定費・サブスクリプション(期間合計は全明細からSUMIFで自動集計)
A3: 項目(利用先) | B3: 区分 | C3: 期間合計(円) | D3: 出現回数 | E3: 月平均(円) | F3: メモ・見直し提案
A4: MLT 0570666020 | B4: 不明・要確認 | C4: =SUMIF(全明細!$E$2:$E$975,"MLT 0570666020",全明細!$G$2:$G$975) -> 443000 | D4: =COUNTIF(全明細!$E$2:$E$975,"MLT 0570666020") -> 9 | E4: =IF(D4=0,0,C4/10) -> 44300 | F4: 毎月20日前後に55,000円。0570-666-020への定額支払。内容不明のため最優先で確認、不要なら解約(年▲66万円)
A5: アフターコールナビ | B5: 電話代行 | C5: =SUMIF(全明細!$E$2:$E$975,"アフターコールナビ",全明細!$G$2:$G$975) -> 1080516 | D5: =COUNTIF(全明細!$E$2:$E$975,"アフターコールナビ") -> 9 | E5: =IF(D5=0,0,C5/10) -> 108051.6 | F5: 月8.6万〜15.6万円(従量?)。fondesk等(月1〜2万円)への切替やプラン見直しで月▲8〜10万円の余地
A6: PAYPAL *ADVANCE STD(ACCOUNTING) | B6: 経理代行 | C6: =SUMIF(全明細!$E$2:$E$975,"PAYPAL *ADVANCE STD(ACCOUNTING)",全明細!$G$2:$G$975) -> 497500 | D6: =COUNTIF(全明細!$E$2:$E$975,"PAYPAL *ADVANCE STD(ACCOUNTING)") -> 14 | E6: =IF(D6=0,0,C6/10) -> 49750 | F6: 2026/1まで月77,500円(50,000+27,500)→2月以降27,500円に減額済み。弥生導入済みなら範囲を再確認
A7: PAYPAL *NKOFFICELLC(CONSULTING) | B7: コンサル | C7: =SUMIF(全明細!$E$2:$E$975,"PAYPAL *NKOFFICELLC(CONSULTING)",全明細!$G$2:$G$975) -> 120000 | D7: =COUNTIF(全明細!$E$2:$E$975,"PAYPAL *NKOFFICELLC(CONSULTING)") -> 4 | E7: =IF(D7=0,0,C7/10) -> 12000 | F7: 毎月1日30,000円。成果と継続要否を確認
A8: バランス大家サロン | B8: オンラインサロン | C8: =SUMIF(全明細!$E$2:$E$975,"バランス大家サロン",全明細!$G$2:$G$975) -> 176000 | D8: =COUNTIF(全明細!$E$2:$E$975,"バランス大家サロン") -> 8 | E8: =IF(D8=0,0,C8/10) -> 17600 | F8: 月22,000円。不動産系サロン4件と重複気味
A9: クラブジャイアンサロン | B9: オンラインサロン | C9: =SUMIF(全明細!$E$2:$E$975,"クラブジャイアンサロン",全明細!$G$2:$G$975) -> 66000 | D9: =COUNTIF(全明細!$E$2:$E$975,"クラブジャイアンサロン") -> 4 | E9: =IF(D9=0,0,C9/10) -> 6600 | F9: 月16,500円
A10: セリック不動産投資道 | B10: オンラインサロン | C10: =SUMIF(全明細!$E$2:$E$975,"セリック不動産投資道",全明細!$G$2:$G$975) -> 86240 | D10: =COUNTIF(全明細!$E$2:$E$975,"セリック不動産投資道") -> 8 | E10: =IF(D10=0,0,C10/10) -> 8624 | F10: 月10,780円
A11: 楽待プレミアム | B11: 不動産情報 | C11: =SUMIF(全明細!$E$2:$E$975,"楽待プレミアム",全明細!$G$2:$G$975) -> 6600 | D11: =COUNTIF(全明細!$E$2:$E$975,"楽待プレミアム") -> 2 | E11: =IF(D11=0,0,C11/10) -> 660 | F11: 月3,300円
A12: MONTHLY GO(レンタカー月額) | B12: 車両 | C12: =SUMIF(全明細!$E$2:$E$975,"MONTHLY GO(レンタカー月額)",全明細!$G$2:$G$975) -> 570680 | D12: =COUNTIF(全明細!$E$2:$E$975,"MONTHLY GO(レンタカー月額)") -> 2 | E12: =IF(D12=0,0,C12/10) -> 57068 | F12: 月27.7万〜29.3万円の月額レンタカー。カーシェア・リース(月5〜10万円)比較で大幅削減余地
A13: ソフトバンクM | B13: 通信 | C13: =SUMIF(全明細!$E$2:$E$975,"ソフトバンクM",全明細!$G$2:$G$975) -> 95328 | D13: =COUNTIF(全明細!$E$2:$E$975,"ソフトバンクM") -> 42 | E13: =IF(D13=0,0,C13/10) -> 9532.8 | F13: 毎月末5回線・計約12,000円/月。回線数の棚卸しと法人プラン統合
A14: GMOとくとくBB | B14: 通信 | C14: =SUMIF(全明細!$E$2:$E$975,"GMOとくとくBB",全明細!$G$2:$G$975) -> 30834 | D14: =COUNTIF(全明細!$E$2:$E$975,"GMOとくとくBB") -> 6 | E14: =IF(D14=0,0,C14/10) -> 3083.4 | F14: 月約5,120円。他回線と重複していないか確認
A15: [BtoB]03Plus / 03Plus | B15: 通信(クラウド電話) | C15: =SUMIF(全明細!$E$2:$E$975,"[BtoB]03Plus",全明細!$G$2:$G$975)+SUMIF(全明細!$E$2:$E$975,"03Plus",全明細!$G$2:$G$975) -> 15697 | D15: =COUNTIF(全明細!$E$2:$E$975,"[BtoB]03Plus")+COUNTIF(全明細!$E$2:$E$975,"03Plus") -> 4 | E15: =IF(D15=0,0,C15/10) -> 1569.7 | F15: 月約3,800円
A16: ドコモご利用料金 | B16: 通信 | C16: =SUMIF(全明細!$E$2:$E$975,"ドコモご利用料金",全明細!$G$2:$G$975) -> 21794 | D16: =COUNTIF(全明細!$E$2:$E$975,"ドコモご利用料金") -> 2 | E16: =IF(D16=0,0,C16/10) -> 2179.4 | F16: 月8,510〜13,284円
A17: Anthropic Claude サブスク | B17: AI | C17: =SUMIF(全明細!$E$2:$E$975,"Anthropic Claude サブスク",全明細!$G$2:$G$975) -> 121024 | D17: =COUNTIF(全明細!$E$2:$E$975,"Anthropic Claude サブスク") -> 5 | E17: =IF(D17=0,0,C17/10) -> 12102.4 | F17: USD22+USD49.5+USD220(Max)が併走した月あり。プラン一本化+年払いで月▲1万円前後
A18: GOOGLE ONE | B18: クラウド | C18: =SUMIF(全明細!$E$2:$E$975,"GOOGLE ONE",全明細!$G$2:$G$975) -> 26100 | D18: =COUNTIF(全明細!$E$2:$E$975,"GOOGLE ONE") -> 9 | E18: =IF(D18=0,0,C18/10) -> 2610 | F18: 月2,900円
A19: YouTube Premium | B19: 動画 | C19: =SUMIF(全明細!$E$2:$E$975,"YouTube Premium",全明細!$G$2:$G$975) -> 11520 | D19: =COUNTIF(全明細!$E$2:$E$975,"YouTube Premium") -> 9 | E19: =IF(D19=0,0,C19/10) -> 1152 | F19: 月1,280円
A20: アドビ | B20: ソフト | C20: =SUMIF(全明細!$E$2:$E$975,"アドビ",全明細!$G$2:$G$975) -> 34860 | D20: =COUNTIF(全明細!$E$2:$E$975,"アドビ") -> 7 | E20: =IF(D20=0,0,C20/10) -> 3486 | F20: 月4,980円
A21: McAfee | B21: セキュリティ | C21: =SUMIF(全明細!$E$2:$E$975,"McAfee",全明細!$G$2:$G$975) -> 12980 | D21: =COUNTIF(全明細!$E$2:$E$975,"McAfee") -> 1 | E21: =IF(D21=0,0,C21/10) -> 1298 | F21: 年12,980円。Windows Defender等で代替可なら解約
A22: MD(MDISM) SERVICE | B22: 不明・要確認 | C22: =SUMIF(全明細!$E$2:$E$975,"MD(MDISM) SERVICE",全明細!$G$2:$G$975) -> 10956 | D22: =COUNTIF(全明細!$E$2:$E$975,"MD(MDISM) SERVICE") -> 2 | E22: =IF(D22=0,0,C22/10) -> 1095.6 | F22: 月5,478円×2回検出。内容確認
A23: Apple iTunes Store / APPLE COM BILL / アマゾンサービシーズ | B23: アプリ・コンテンツ課金 | C23: =SUMIF(全明細!$E$2:$E$975,"Apple iTunes Store",全明細!$G$2:$G$975)+SUMIF(全明細!$E$2:$E$975,"APPLE COM BILL",全明細!$G$2:$G$975)+SUMIF(全明細!$E$2:$E$975,"アマゾンサービシーズ",全明細!$G$2:$G$975) -> 88324 | D23: =COUNTIF(全明細!$E$2:$E$975,"Apple iTunes Store")+COUNTIF(全明細!$E$2:$E$975,"APPLE COM BILL")+COUNTIF(全明細!$E$2:$E$975,"アマゾンサービシーズ") -> 42 | E23: =IF(D23=0,0,C23/10) -> 8832.4 | F23: 月平均約1万円。サブスク棚卸し(Apple設定→サブスクリプションで一覧確認)
A24: GOアプリ(プレミアム) | B24: タクシーアプリ | C24: =SUMIF(全明細!$E$2:$E$975,"GOアプリ(プレミアム)",全明細!$G$2:$G$975) -> 2500 | D24: =COUNTIF(全明細!$E$2:$E$975,"GOアプリ(プレミアム)") -> 1 | E24: =IF(D24=0,0,C24/10) -> 250 | F24: 月2,500円。利用頻度と特典を確認
A25: エキスパ | B25: 配信ツール | C25: =SUMIF(全明細!$E$2:$E$975,"エキスパ",全明細!$G$2:$G$975) -> 29800 | D25: =COUNTIF(全明細!$E$2:$E$975,"エキスパ") -> 1 | E25: =IF(D25=0,0,C25/10) -> 2980 | F25: 29,800円。利用実態確認
A26: 弥生株式会社 | B26: 会計ソフト | C26: =SUMIF(全明細!$E$2:$E$975,"弥生株式会社",全明細!$G$2:$G$975) -> 74470 | D26: =COUNTIF(全明細!$E$2:$E$975,"弥生株式会社") -> 1 | E26: =IF(D26=0,0,C26/10) -> 7447 | F26: 年74,470円
A27: 24/7Workout / 24/7Workout ONLINESHOP | B27: パーソナルジム | C27: =SUMIF(全明細!$E$2:$E$975,"24/7Workout",全明細!$G$2:$G$975)+SUMIF(全明細!$E$2:$E$975,"24/7Workout ONLINESHOP",全明細!$G$2:$G$975) -> 151096 | D27: =COUNTIF(全明細!$E$2:$E$975,"24/7Workout")+COUNTIF(全明細!$E$2:$E$975,"24/7Workout ONLINESHOP") -> 7 | E27: =IF(D27=0,0,C27/10) -> 15109.6 | F27: 月約37,000円
A28: HEARTLIFE こころの悩み相談所 / Square(HeartLife こころの悩み相談) | B28: カウンセリング | C28: =SUMIF(全明細!$E$2:$E$975,"HEARTLIFE こころの悩み相談所",全明細!$G$2:$G$975)+SUMIF(全明細!$E$2:$E$975,"Square(HeartLife こころの悩み相談)",全明細!$G$2:$G$975) -> 41800 | D28: =COUNTIF(全明細!$E$2:$E$975,"HEARTLIFE こころの悩み相談所")+COUNTIF(全明細!$E$2:$E$975,"Square(HeartLife こころの悩み相談)") -> 5 | E28: =IF(D28=0,0,C28/10) -> 4180 | F28: 月6,600〜8,800円
A29: エクスプレス予約 年会費 | B29: 新幹線予約 | C29: =SUMIF(全明細!$E$2:$E$975,"エクスプレス予約 年会費",全明細!$G$2:$G$975) -> 1100 | D29: =COUNTIF(全明細!$E$2:$E$975,"エクスプレス予約 年会費") -> 1 | E29: =IF(D29=0,0,C29/10) -> 110 | F29: 年1,100円(継続推奨・割引効果大)
A30: プラチナカード年会費 | B30: カード年会費 | C30: =SUMIF(全明細!$E$2:$E$975,"プラチナカード年会費",全明細!$G$2:$G$975) -> 96800 | D30: =COUNTIF(全明細!$E$2:$E$975,"プラチナカード年会費") -> 1 | E30: =IF(D30=0,0,C30/10) -> 9680 | F30: ANA VISAプラチナ96,800円/年。マイル・還元価値と利用実態を照らし、ゴールド等へのダウングレード検討
A31: セリック不動産投資道 / バランス大家サロン / クラブジャイアンサロン / 楽待プレミアム | B31: サロン・情報費合算 | C31: =SUMIF(全明細!$E$2:$E$975,"セリック不動産投資道",全明細!$G$2:$G$975)+SUMIF(全明細!$E$2:$E$975,"バランス大家サロン",全明細!$G$2:$G$975)+SUMIF(全明細!$E$2:$E$975,"クラブジャイアンサロン",全明細!$G$2:$G$975)+SUMIF(全明細!$E$2:$E$975,"楽待プレミアム",全明細!$G$2:$G$975) -> 334840 | D31: =COUNTIF(全明細!$E$2:$E$975,"セリック不動産投資道")+COUNTIF(全明細!$E$2:$E$975,"バランス大家サロン")+COUNTIF(全明細!$E$2:$E$975,"クラブジャイアンサロン")+COUNTIF(全明細!$E$2:$E$975,"楽待プレミアム") -> 22 | E31: =IF(D31=0,0,C31/10) -> 33484 | F31: 月合計約52,000円 → 実際に収益に繋がっているもの2つ程度に絞ると月▲2.5〜3万円
A33: ※ 月平均は対象期間を約10ヶ月として単純計算。

Sheet 経費削減提案
A1: 経費削減提案(優先度順)— 試算はすべて全明細シートの実績に基づく概算
A3: 優先度 | B3: 施策 | C3: 現状(実績) | D3: 提案内容 | E3: 削減見込み(月) | F3: 削減見込み(年)
A4: ★★★ | B4: MLT(0570-666-020)への月額55,000円の解明 | C4: 毎月55,000円×8回+3,000円=443,000円(内容不明) | D4: 請求元へ電話確認し、不要契約なら即解約。身に覚えがなければカード会社へ調査依頼 | E4: 55000 | F4: =E4*12 -> 660000
A5: ★★★ | B5: 電話代行(アフターコールナビ)の見直し | C5: 月86,495〜155,909円・10ヶ月で約108万円 | D5: 従量プランの単価・コール数を精査。fondesk(月1〜2万円)等への切替、営業時間外のみ利用などで圧縮 | E5: 80000 | F5: =E5*12 -> 960000
A6: ★★★ | B6: 月額レンタカー(MONTHLY GO)の代替 | C6: 3月293,480円・6月277,200円 | D6: 利用日数を集計し、カーシェア/短期レンタル/リース(月5〜10万円)と比較。ETC・ガソリン・駐車場込みで車両費は期間合計約80万円 | E6: 100000 | F6: =E6*12 -> 1200000
A7: ★★ | B7: 不動産系サロン・情報費の絞り込み | C7: バランス大家22,000+ジャイアン16,500+セリック10,780+楽待3,300=月約52,600円 | D7: 収益貢献が明確な1〜2件に絞る | E7: 28000 | F7: =E7*12 -> 336000
A8: ★★ | B8: AIサブスクの一本化 | C8: Claude USD22+USD49.5+USD220が併走した月あり(月最大約4.7万円) | D8: Maxプラン1本に統合し重複分を解約。年払い割引も検討 | E8: 12000 | F8: =E8*12 -> 144000
A9: ★★ | B9: 経理代行とスポット外注の整理 | C9: 経理代行27,500円/月+クラウドワークス月平均約3.7万円+ココナラ計17万円 | D9: 弥生(年74,470円契約済み)の自動仕訳を活用し記帳代行の範囲縮小。外注は発注単価の相見積を徹底 | E9: 20000 | F9: =E9*12 -> 240000
A10: ★★ | B10: 通信回線の統合 | C10: SoftBank5回線(約12,000円)+ドコモ(約1万円)+GMO(5,120円)+03Plus(約3,800円)=月約3.1万円 | D10: 回線棚卸しで未使用回線解約、法人まとめプランへ。GMOは光回線と重複していないか確認 | E10: 12000 | F10: =E10*12 -> 144000
A11: ★ | B11: 小口サブスクの棚卸し | C11: Adobe4,980+Google One2,900+YouTube1,280+McAfee(年12,980)+MD5,478×2+GOプレミアム2,500+Apple課金 月平均約1万円 | D11: 使っていないものを解約。Adobeは単体プラン/Photoshop版(月3,280円)へ変更検討 | E11: 10000 | F11: =E11*12 -> 120000
A12: ★ | B12: カード年会費の見直し | C12: ANA VISAプラチナ96,800円/年+Marriott AMEX(約49,500円/年) | D12: マイル・ポイント還元額と年会費を比較。片方をゴールド以下へ変更で年5〜10万円削減 | E12: 8000 | F12: =E12*12 -> 96000
A13: ★ | B13: 飲食費の経費区分の明確化 | C13: 飲食費は期間合計約80万円(鷹丸鮮魚店ほぼ毎日1,380〜1,980円、えごたいえ等) | D13: 事業関連(会議・接待)と私的飲食を分け、私的分は事業主貸へ。税務リスク低減+実質支出の見える化 | E13: 0 | F13: =E13*12 -> 0
A14: ★ | B14: 税金カード納付の手数料検証 | C14: eLTAXシステム利用料 計44,254円(手数料率約0.8%) | D14: カード還元率が手数料率を上回るか確認。下回る場合はダイレクト納付(手数料0円)へ | E14: 2000 | F14: =E14*12 -> 24000
A15: - | B15: 新幹線・出張費 | C15: エクスプレス予約 期間合計約40万円(名古屋方面ほぼ毎週) | D15: EX予約は既に割安。出張頻度そのものの見直しやオンライン商談併用で更に圧縮可 | E15: 0 | F15: =E15*12 -> 0
B16: 削減見込み合計 | E16: =SUM(E4:E15) -> 327000 | F16: =SUM(F4:F15) -> 3924000
A18: ※ 削減見込みは実績に基づく概算(青字=入力値)。実行前に各契約内容をご確認ください。
A19: ※ 租税公課(税金)は削減対象外として提案から除外(期間合計は科目別集計シート参照)。
